{"name": "EC-EARTH3-LR", "meta": {"institute": "ec-earth-consortium", "createDate": "2020-04-08 13:15:00.301733", "project": "cmip6", "source": "spreadsheet", "version": 1, "type": "cim.2.science.Model", "id": "a74342f8-eda5-4793-9ab5-c711762e1c27"}, "canonicalID": "ec-earth3-lr", "modelType": "GCM", "keyProperties": {"meta": {"type": "cim.2.science.Topic"}, "specializationID": "cmip6.toplevel.key_properties", "properties": [{"values": ["EC-Earth3-LR"], "meta": {"type": "cim.2.science.TopicProperty"}, "specializationID": "cmip6.toplevel.key_properties.name"}, {"values": ["See Doescher-et-al-2020. Fields with an identical description for this EC-Earth3-LR configaration as for the EC-Earth3 configuration are left empty."], "meta": {"type": "cim.2.science.TopicProperty"}, "specializationID": "cmip6.toplevel.key_properties.overview"}]}}